{
  "url" : "https://github.com/apache/commons-rdf/pull/121",
  "project" : "commons-rdf",
  "commit" : "00063ce5d656166afc755a5a4fc765b439c1b8d3",
  "createdAt" : "2023-02-10T19:58:59.000+00:00",
  "dependencyGroupID" : "org.glassfish.jaxb",
  "dependencyArtifactID" : "jaxb-runtime",
  "previousVersion" : "2.3.6",
  "newVersion" : "4.0.2",
  "dependencyScope" : "unknown",
  "versionUpdateType" : "major",
  "prAuthor" : "bot",
  "preCommitAuthor" : "human",
  "breakingCommitAuthor" : "human",
  "baseBuildCommand" : null,
  "breakingUpdateReproductionCommand" : null,
  "reproductionStatus" : "not_attempted",
  "analysis" : null,
  "metadata" : null
}