{
  "url": "https://github.com/artipie/asto/pull/447",
  "project": "asto",
  "commit": "0120294376f3f19367eeb083e3bff7a1eedfdf59",
  "createdAt": "2022-07-20 14:19:32",
  "dependency": "org.eclipse.jetty",
  "previousVersion": "9.4.45.v20220203",
  "newVersion": "9.4.48.v20220622",
  "versionUpdateType": "other",
  "type": "dependabot",
  "reproductionStatus": "unreproducible",
  "analysis": {
    "labels": [
      "PRECEDING_COMMIT_TEST_FAILURE"
    ],
    "javaVersionUsedForReproduction": "11",
    "reproductionLogLocation": "reproduction/unreproducible/0120294376f3f19367eeb083e3bff7a1eedfdf59.log"
  }
}