{
  "url": "https://github.com/apache/commons-jcs/pull/107",
  "project": "commons-jcs",
  "commit": "0202fb42893931eff47188b8eac561352addbbb4",
  "createdAt": "2022-09-23T07:06:30.000+00:00",
  "dependencyGroupID": "org.apache.logging.log4j",
  "dependencyArtifactID": "log4j-api",
  "previousVersion": "2.18.0",
  "newVersion": "2.19.0",
  "versionUpdateType": "minor",
  "type": "dependabot",
  "reproductionStatus": "unreproducible",
  "analysis": {
    "labels": [
      "NO_FAILURE"
    ],
    "javaVersionUsedForReproduction": "11",
    "reproductionLogLocation": "https://github.com/chains-project/breaking-updates/blob/main/reproduction/unreproducible/0202fb42893931eff47188b8eac561352addbbb4.log"
  }
}