{
  "url": "https://github.com/artipie/npm-adapter/pull/318",
  "project": "npm-adapter",
  "commit": "023ea92537583a454f9b59fb0da9729983fb9031",
  "createdAt": "2022-04-22T08:11:20.000+00:00",
  "dependencyGroupID": "org.mockito",
  "dependencyArtifactID": "mockito-junit-jupiter",
  "previousVersion": "4.1.0",
  "newVersion": "4.5.1",
  "versionUpdateType": "minor",
  "type": "dependabot",
  "reproductionStatus": "unreproducible",
  "analysis": {
    "labels": [
      "NO_FAILURE"
    ],
    "javaVersionUsedForReproduction": "11",
    "reproductionLogLocation": "https://github.com/chains-project/breaking-updates/blob/main/reproduction/unreproducible/023ea92537583a454f9b59fb0da9729983fb9031.log"
  }
}