{
  "url": "https://github.com/jiangxincode/ApkToolBoxGUI/pull/59",
  "project": "ApkToolBoxGUI",
  "commit": "02d65fb06955a89f460d34c1edfbd372b0d306c1",
  "createdAt": "2021-12-18 18:09:49",
  "dependency": "org.apache.logging.log4j",
  "previousVersion": "2.16.0",
  "newVersion": "2.17.0",
  "versionUpdateType": "minor",
  "type": "dependabot",
  "reproductionStatus": "unreproducible",
  "analysis": {
    "labels": [
      "NO_FAILURE"
    ],
    "javaVersionUsedForReproduction": "11",
    "reproductionLogLocation": "reproduction/unreproducible/02d65fb06955a89f460d34c1edfbd372b0d306c1.log"
  }
}