{
  "url": "https://github.com/btrplace/scheduler/pull/286",
  "project": "scheduler",
  "commit": "052b9e4cc43c9496a7fb10bdb304de5c92649c01",
  "createdAt": "2021-04-19 07:10:15",
  "dependency": "net.minidev",
  "previousVersion": "2.4.2",
  "newVersion": "2.4.4",
  "versionUpdateType": "patch",
  "type": "dependabot",
  "reproductionStatus": "successful",
  "analysis": {
    "labels": [
      "COMPILATION_FAILURE"
    ],
    "javaVersionUsedForReproduction": "11",
    "reproductionLogLocation": "./reproduction/successful/052b9e4cc43c9496a7fb10bdb304de5c92649c01.log"
  }
}