{
  "url": "https://github.com/premium-minds/wicket-crudifier/pull/67",
  "project": "wicket-crudifier",
  "commit": "07a5964eb756ced38d7f079e27acfc5021cc331b",
  "createdAt": "2022-10-17 23:10:04",
  "dependency": "org.easymock",
  "previousVersion": "4.3",
  "newVersion": "5.0.0",
  "versionUpdateType": "other",
  "type": "dependabot",
  "reproductionStatus": "successful",
  "analysis": {
    "labels": [
      "TEST_FAILURE"
    ],
    "javaVersionUsedForReproduction": "11",
    "reproductionLogLocation": "reproduction/successful/07a5964eb756ced38d7f079e27acfc5021cc331b.log"
  }
}