{
  "url": "https://github.com/Marketcetera/marketcetera/pull/796",
  "project": "marketcetera",
  "commit": "0a9657f418a8dd59ff99ec351c7f0367eb417bf8",
  "createdAt": "2022-02-17T13:53:04.000+00:00",
  "dependencyGroupID": "commons-cli",
  "dependencyArtifactID": "commons-cli",
  "previousVersion": "1.4",
  "newVersion": "1.5.0",
  "versionUpdateType": "other",
  "type": "dependabot",
  "reproductionStatus": "unreproducible",
  "analysis": {
    "labels": [
      "PRECEDING_COMMIT_COMPILATION_FAILURE"
    ],
    "javaVersionUsedForReproduction": "11",
    "reproductionLogLocation": "reproduction/unreproducible/0a9657f418a8dd59ff99ec351c7f0367eb417bf8.log"
  }
}