{
  "url": "https://github.com/apache/maven-jlink-plugin/pull/89",
  "project": "maven-jlink-plugin",
  "commit": "0b0c6b82fc99ed6f8967d6def8133166a8ecf0e8",
  "createdAt": "2022-01-12 04:05:47",
  "dependency": "org.assertj",
  "previousVersion": "3.21.0",
  "newVersion": "3.22.0",
  "versionUpdateType": "minor",
  "type": "dependabot",
  "reproductionStatus": "unreproducible",
  "analysis": {
    "labels": [
      "NO_FAILURE"
    ],
    "javaVersionUsedForReproduction": "11",
    "reproductionLogLocation": "reproduction/unreproducible/0b0c6b82fc99ed6f8967d6def8133166a8ecf0e8.log"
  }
}