{
  "url": "https://github.com/googleapis/java-dlp/pull/436",
  "project": "java-dlp",
  "commit": "16ad97f2b0c2fae541d036439e6e119bad92af1a",
  "createdAt": "2021-02-25T00:07:57.000+00:00",
  "dependencyGroupID": "com.google.cloud",
  "dependencyArtifactID": "libraries-bom",
  "previousVersion": "17.0.0",
  "newVersion": "18.0.0",
  "versionUpdateType": "major",
  "type": "renovate",
  "reproductionStatus": "unreproducible",
  "analysis": {
    "labels": [
      "NO_FAILURE"
    ],
    "javaVersionUsedForReproduction": "11",
    "reproductionLogLocation": "https://github.com/chains-project/breaking-updates/blob/main/reproduction/unreproducible/16ad97f2b0c2fae541d036439e6e119bad92af1a.log"
  }
}