{
  "url" : "https://github.com/jenkinsci/configuration-as-code-plugin/pull/1820",
  "project" : "configuration-as-code-plugin",
  "commit" : "1c56f20a16d810d322037b3eb6cd4ea5466897e1",
  "createdAt" : "2021-12-21T12:00:16.000+00:00",
  "dependencyGroupID" : "org.jenkins-ci.plugins",
  "dependencyArtifactID" : "gitlab-plugin",
  "previousVersion" : "1.5.20",
  "newVersion" : "1.5.25",
  "dependencyScope" : "unknown",
  "versionUpdateType" : "patch",
  "prAuthor" : "bot",
  "preCommitAuthor" : "bot",
  "breakingCommitAuthor" : "bot",
  "baseBuildCommand" : null,
  "breakingUpdateReproductionCommand" : null,
  "reproductionStatus" : "not_attempted",
  "analysis" : null,
  "metadata" : null
}