{
  "url": "https://github.com/Pante/elementary/pull/104",
  "project": "elementary",
  "commit": "1d9dcecdb26004439602316909acab0f79e35446",
  "createdAt": "2022-04-21 21:12:19",
  "dependency": "org.mockito",
  "previousVersion": "4.5.0",
  "newVersion": "4.5.1",
  "versionUpdateType": "patch",
  "type": "dependabot",
  "reproductionStatus": "unreproducible",
  "analysis": {
    "labels": [
      "PRECEDING_COMMIT_COMPILATION_FAILURE"
    ],
    "javaVersionUsedForReproduction": "11",
    "reproductionLogLocation": "./reproduction/unreproducible/1d9dcecdb26004439602316909acab0f79e35446.log"
  }
}