{
  "url": "https://github.com/Pante/elementary/pull/138",
  "project": "elementary",
  "commit": "1e960fe1ddd20da35bf1b73a0c27776b5d40d743",
  "createdAt": "2022-09-20T21:13:48.000+00:00",
  "dependencyGroupID": "org.junit.jupiter",
  "dependencyArtifactID": "junit-jupiter-params",
  "previousVersion": "5.9.0",
  "newVersion": "5.9.1",
  "versionUpdateType": "patch",
  "type": "dependabot",
  "reproductionStatus": "unreproducible",
  "analysis": {
    "labels": [
      "PRECEDING_COMMIT_COMPILATION_FAILURE"
    ],
    "javaVersionUsedForReproduction": "11",
    "reproductionLogLocation": "https://github.com/chains-project/breaking-updates/blob/main/reproduction/unreproducible/1e960fe1ddd20da35bf1b73a0c27776b5d40d743.log"
  }
}