{
  "url": "https://github.com/informatici/openhospital-core/pull/222",
  "project": "openhospital-core",
  "commit": "2154ea156aec0e8584b6440542b28292151c5287",
  "createdAt": "2020-10-01 04:59:03",
  "dependency": "org.hibernate",
  "previousVersion": "4.2.5.Final",
  "newVersion": "5.4.22.Final",
  "versionUpdateType": "other",
  "type": "dependabot",
  "reproductionStatus": "unreproducible",
  "analysis": {
    "labels": [
      "PRECEDING_COMMIT_TEST_FAILURE"
    ],
    "javaVersionUsedForReproduction": "11",
    "reproductionLogLocation": "./reproduction/unreproducible/2154ea156aec0e8584b6440542b28292151c5287.log"
  }
}