{
  "url": "https://github.com/comixed/comixed/pull/1405",
  "project": "comixed",
  "commit": "216a35f0e4fa00b57c8ccd31105503b9139b9626",
  "createdAt": "2022-09-02 01:53:50",
  "dependency": "org.jsoup",
  "artifactId": "jsoup",
  "groupId": "org.jsoup",
  "previousVersion": "1.14.3",
  "newVersion": "1.15.3",
  "versionUpdateType": "minor",
  "type": "dependabot",
  "reproductionStatus": "unreproducible",
  "analysis": {
    "labels": [
      "PRECEDING_COMMIT_TEST_FAILURE"
    ],
    "javaVersionUsedForReproduction": "11",
    "reproductionLogLocation": "./reproduction/unreproducible/216a35f0e4fa00b57c8ccd31105503b9139b9626.log"
  }
}