{
  "url": "https://github.com/AppiumTestDistribution/AppiumTestDistribution/pull/949",
  "project": "AppiumTestDistribution",
  "commit": "23ee97dca9e1df94006b86a21532290c89aaabbd",
  "createdAt": "2022-05-02 18:01:41",
  "dependency": "io.cucumber",
  "previousVersion": "6.9.1",
  "newVersion": "7.3.3",
  "versionUpdateType": "major",
  "type": "dependabot",
  "reproductionStatus": "unreproducible",
  "analysis": {
    "labels": [
      "PRECEDING_COMMIT_TEST_FAILURE"
    ],
    "javaVersionUsedForReproduction": "11",
    "reproductionLogLocation": "reproduction/unreproducible/23ee97dca9e1df94006b86a21532290c89aaabbd.log"
  }
}