{
  "url": "https://github.com/alphagov/pay-connector/pull/4049",
  "project": "pay-connector",
  "commit": "23fd089d9036b7d1510a5f347b17f1a1e6b02f21",
  "createdAt": "2022-09-28T03:01:08.000+00:00",
  "dependencyGroupID": "com.amazonaws",
  "dependencyArtifactID": "aws-java-sdk-sqs",
  "previousVersion": "1.12.303",
  "newVersion": "1.12.312",
  "versionUpdateType": "patch",
  "type": "dependabot",
  "reproductionStatus": "unreproducible",
  "analysis": {
    "labels": [
      "NO_FAILURE"
    ],
    "javaVersionUsedForReproduction": "11",
    "reproductionLogLocation": "https://github.com/chains-project/breaking-updates/blob/main/reproduction/unreproducible/23fd089d9036b7d1510a5f347b17f1a1e6b02f21.log"
  }
}