{
  "url": "https://github.com/GoogleCloudPlatform/bank-of-anthos/pull/477",
  "project": "bank-of-anthos",
  "commit": "2bec449459178d449e8c96c69915802da93871fb",
  "createdAt": "2021-03-31 22:12:41",
  "dependency": "com.google.guava",
  "previousVersion": "28.2-jre",
  "newVersion": "29.0-jre",
  "versionUpdateType": "other",
  "type": "dependabot",
  "reproductionStatus": "unreproducible",
  "analysis": {
    "labels": [
      "NO_FAILURE"
    ],
    "javaVersionUsedForReproduction": "11",
    "reproductionLogLocation": "reproduction/unreproducible/2bec449459178d449e8c96c69915802da93871fb.log"
  }
}