{
  "url": "https://github.com/googleapis/gax-java/pull/1774",
  "project": "gax-java",
  "commit": "3ff6542403c6b3baa0be6f100fc0c472ab169996",
  "createdAt": "2022-08-13 13:21:01",
  "dependencyGroupID": "org.mockito",
  "dependencyArtifactID": "mockito-core",
  "previousVersion": "4.6.1",
  "newVersion": "4.7.0",
  "versionUpdateType": "minor",
  "type": "renovate",
  "reproductionStatus": "unreproducible",
  "analysis": {
    "labels": [
      "NO_FAILURE"
    ],
    "javaVersionUsedForReproduction": "11",
    "reproductionLogLocation": "reproduction/unreproducible/3ff6542403c6b3baa0be6f100fc0c472ab169996.log"
  }
}