{
  "url": "https://github.com/Hack23/cia/pull/4479",
  "project": "cia",
  "commit": "419e369a3d017797bfe57bfc4fd0ad46faa87f2f",
  "createdAt": "2022-07-27 09:38:48",
  "dependency": "org.junit.vintage",
  "previousVersion": "5.9.0-RC1",
  "newVersion": "5.9.0",
  "versionUpdateType": "other",
  "type": "dependabot",
  "reproductionStatus": "unreproducible",
  "analysis": {
    "labels": [
      "PRECEDING_COMMIT_COMPILATION_FAILURE"
    ],
    "javaVersionUsedForReproduction": "11",
    "reproductionLogLocation": "./reproduction/unreproducible/419e369a3d017797bfe57bfc4fd0ad46faa87f2f.log"
  }
}