{
  "url": "https://github.com/AxonIQ/code-samples/pull/184",
  "project": "code-samples",
  "commit": "45db471fd60f3b6b62e6537109b67e081da4206b",
  "createdAt": "2022-05-30 04:05:21",
  "dependency": "org.mockito",
  "previousVersion": "3.12.4",
  "newVersion": "4.6.0",
  "versionUpdateType": "major",
  "type": "dependabot",
  "reproductionStatus": "unreproducible",
  "analysis": {
    "labels": [
      "PRECEDING_COMMIT_TEST_FAILURE"
    ],
    "javaVersionUsedForReproduction": "11",
    "reproductionLogLocation": "reproduction/unreproducible/45db471fd60f3b6b62e6537109b67e081da4206b.log"
  }
}