{
  "url": "https://github.com/jenkinsci/warnings-ng-plugin/pull/1359",
  "project": "warnings-ng-plugin",
  "commit": "4b832b5984400341c66e10445e03444990104779",
  "createdAt": "2022-09-22T09:02:46.000+00:00",
  "dependencyGroupID": "io.jenkins.plugins",
  "dependencyArtifactID": "bootstrap5-api",
  "previousVersion": "5.2.0-3",
  "newVersion": "5.2.1-2",
  "versionUpdateType": "other",
  "type": "dependabot",
  "reproductionStatus": "unreproducible",
  "analysis": {
    "labels": [
      "PRECEDING_COMMIT_TEST_FAILURE"
    ],
    "javaVersionUsedForReproduction": "11",
    "reproductionLogLocation": "https://github.com/chains-project/breaking-updates/blob/main/reproduction/unreproducible/4b832b5984400341c66e10445e03444990104779.log"
  }
}