{
  "url": "https://github.com/Inform-Software/sonar-groovy/pull/156",
  "project": "sonar-groovy",
  "commit": "4e834e409d96d062c00c34abd33d3b2908d3469a",
  "createdAt": "2022-07-04 20:02:04",
  "dependency": "com.fasterxml.woodstox",
  "previousVersion": "5.2.1",
  "newVersion": "6.3.0",
  "versionUpdateType": "major",
  "type": "dependabot",
  "reproductionStatus": "unreproducible",
  "analysis": {
    "labels": [
      "NO_FAILURE"
    ],
    "javaVersionUsedForReproduction": "11",
    "reproductionLogLocation": "reproduction/unreproducible/4e834e409d96d062c00c34abd33d3b2908d3469a.log"
  }
}