{
  "url": "https://github.com/abstratt/cloudfier/pull/286",
  "project": "cloudfier",
  "commit": "4fbf2fa38f64b24951b9b6045417e85cc7c263a8",
  "createdAt": "2021-09-06 04:30:27",
  "dependency": "org.apache.derby",
  "previousVersion": "10.11.1.1",
  "newVersion": "10.16.1.1",
  "versionUpdateType": "other",
  "type": "renovate",
  "reproductionStatus": "unreproducible",
  "analysis": {
    "labels": [
      "PRECEDING_COMMIT_COMPILATION_FAILURE"
    ],
    "javaVersionUsedForReproduction": "11",
    "reproductionLogLocation": "./reproduction/unreproducible/4fbf2fa38f64b24951b9b6045417e85cc7c263a8.log"
  }
}