{
  "url": "https://github.com/mirkosertic/MogwaiERDesignerNG/pull/198",
  "project": "MogwaiERDesignerNG",
  "commit": "52b80e32c5ce4a26ebc7eee816d372c1980227d6",
  "createdAt": "2021-12-09 04:13:13",
  "dependency": "org.hibernate",
  "previousVersion": "3.5.6-Final",
  "newVersion": "5.6.2.Final",
  "versionUpdateType": "other",
  "type": "dependabot",
  "reproductionStatus": "unreproducible",
  "analysis": {
    "labels": [
      "PRECEDING_COMMIT_COMPILATION_FAILURE"
    ],
    "javaVersionUsedForReproduction": "11",
    "reproductionLogLocation": "./reproduction/unreproducible/52b80e32c5ce4a26ebc7eee816d372c1980227d6.log"
  }
}