{
  "url": "https://github.com/kcctl/kcctl/pull/178",
  "project": "kcctl",
  "commit": "52d19cee99898049bdc3e0f049c5b1f53bf3e573",
  "createdAt": "2022-04-19T20:16:00.000+00:00",
  "dependencyGroupID": "com.squareup.okio",
  "dependencyArtifactID": "okio",
  "previousVersion": "2.8.0",
  "newVersion": "3.1.0",
  "versionUpdateType": "major",
  "type": "dependabot",
  "reproductionStatus": "unreproducible",
  "analysis": {
    "labels": [
      "PRECEDING_COMMIT_COMPILATION_FAILURE"
    ],
    "javaVersionUsedForReproduction": "11",
    "reproductionLogLocation": "reproduction/unreproducible/52d19cee99898049bdc3e0f049c5b1f53bf3e573.log"
  }
}