{
  "url": "https://github.com/btrplace/scheduler/pull/385",
  "project": "scheduler",
  "commit": "544628b905cc7f6dead93a3b02bdc1f33bfc1169",
  "createdAt": "2022-04-20 05:03:15",
  "dependency": "org.mockito",
  "previousVersion": "4.4.0",
  "newVersion": "4.5.0",
  "versionUpdateType": "minor",
  "type": "dependabot",
  "reproductionStatus": "unreproducible",
  "analysis": {
    "labels": [
      "NO_FAILURE"
    ],
    "javaVersionUsedForReproduction": "11",
    "reproductionLogLocation": "./reproduction/unreproducible/544628b905cc7f6dead93a3b02bdc1f33bfc1169.log"
  }
}