{
  "url": "https://github.com/mirkosertic/MogwaiERDesignerNG/pull/159",
  "project": "MogwaiERDesignerNG",
  "commit": "59bb283b18838ee42cbfbc81dc2b9ecd38944c8f",
  "createdAt": "2021-05-05 12:27:38",
  "dependencyGroupID": "org.hsqldb",
  "dependencyArtifactID": "hsqldb",
  "previousVersion": "2.2.4",
  "newVersion": "2.6.0",
  "versionUpdateType": "minor",
  "type": "dependabot",
  "reproductionStatus": "unreproducible",
  "analysis": {
    "labels": [
      "PRECEDING_COMMIT_COMPILATION_FAILURE"
    ],
    "javaVersionUsedForReproduction": "11",
    "reproductionLogLocation": "reproduction/unreproducible/59bb283b18838ee42cbfbc81dc2b9ecd38944c8f.log"
  }
}