{
  "url": "https://github.com/paulcwarren/spring-content-examples/pull/467",
  "project": "spring-content-examples",
  "commit": "601e95cbb35de884e4f9903eaea74c7db1b3a87b",
  "createdAt": "2022-05-24 22:23:35",
  "dependencyGroupID": "software.amazon.awssdk",
  "dependencyArtifactID": "netty-nio-client",
  "previousVersion": "2.17.182",
  "newVersion": "2.17.198",
  "versionUpdateType": "patch",
  "type": "dependabot",
  "reproductionStatus": "unreproducible",
  "analysis": {
    "labels": [
      "PRECEDING_COMMIT_TEST_FAILURE"
    ],
    "javaVersionUsedForReproduction": "11",
    "reproductionLogLocation": "reproduction/unreproducible/601e95cbb35de884e4f9903eaea74c7db1b3a87b.log"
  }
}