{
  "url": "https://github.com/eXist-db/exist/pull/3672",
  "project": "exist",
  "commit": "6102e867d07744c0550d52b263adde3101dab812",
  "createdAt": "2020-12-14 03:21:13",
  "dependency": "org.jline",
  "previousVersion": "3.17.1",
  "newVersion": "3.18.0",
  "versionUpdateType": "minor",
  "type": "dependabot",
  "reproductionStatus": "unreproducible",
  "analysis": {
    "labels": [
      "PRECEDING_COMMIT_COMPILATION_FAILURE"
    ],
    "javaVersionUsedForReproduction": "11",
    "reproductionLogLocation": "reproduction/unreproducible/6102e867d07744c0550d52b263adde3101dab812.log"
  }
}