{
  "url": "https://github.com/dodie/scott/pull/103",
  "project": "scott",
  "commit": "6140f53027718b00d1ea5c9aaf4c2d0d28f9467c",
  "createdAt": "2020-10-13T08:46:28.000+00:00",
  "dependencyGroupID": "junit",
  "dependencyArtifactID": "junit",
  "previousVersion": "4.12",
  "newVersion": "4.13.1",
  "versionUpdateType": "other",
  "type": "dependabot",
  "reproductionStatus": "unreproducible",
  "analysis": {
    "labels": [
      "PRECEDING_COMMIT_TEST_FAILURE"
    ],
    "javaVersionUsedForReproduction": "11",
    "reproductionLogLocation": "https://github.com/chains-project/breaking-updates/blob/main/reproduction/unreproducible/6140f53027718b00d1ea5c9aaf4c2d0d28f9467c.log"
  }
}