{
  "url": "https://github.com/KengoTODA/findbugs-slf4j/pull/456",
  "project": "findbugs-slf4j",
  "commit": "61f77df15528c3dd77cb9977e05da0841f8dde26",
  "createdAt": "2022-05-30 14:02:18",
  "dependency": "org.mockito",
  "previousVersion": "4.5.1",
  "newVersion": "4.6.0",
  "versionUpdateType": "minor",
  "type": "dependabot",
  "reproductionStatus": "unreproducible",
  "analysis": {
    "labels": [
      "PRECEDING_COMMIT_TEST_FAILURE"
    ],
    "javaVersionUsedForReproduction": "11",
    "reproductionLogLocation": "reproduction/unreproducible/61f77df15528c3dd77cb9977e05da0841f8dde26.log"
  }
}