{
  "url": "https://github.com/apache/maven-dependency-plugin/pull/157",
  "project": "maven-dependency-plugin",
  "commit": "6268ce4704e87bf97266c27e175e5884660c6d84",
  "createdAt": "2021-08-24T22:01:01.000+00:00",
  "dependencyGroupID": "org.mockito",
  "dependencyArtifactID": "mockito-core",
  "previousVersion": "2.28.2",
  "newVersion": "3.12.3",
  "versionUpdateType": "major",
  "type": "dependabot",
  "reproductionStatus": "unreproducible",
  "analysis": {
    "labels": [
      "NO_FAILURE"
    ],
    "javaVersionUsedForReproduction": "11",
    "reproductionLogLocation": "https://github.com/chains-project/breaking-updates/blob/main/reproduction/unreproducible/6268ce4704e87bf97266c27e175e5884660c6d84.log"
  }
}