{
  "url": "https://github.com/Marketcetera/marketcetera/pull/1000",
  "project": "marketcetera",
  "commit": "672d6123262b791a0a625c53470fad644e44871a",
  "createdAt": "2022-09-20 01:30:10",
  "dependencyGroupID": "io.grpc",
  "dependencyArtifactID": "grpc-netty",
  "previousVersion": "1.44.1",
  "newVersion": "1.49.1",
  "versionUpdateType": "minor",
  "type": "dependabot",
  "reproductionStatus": "unreproducible",
  "analysis": {
    "labels": [
      "PRECEDING_COMMIT_COMPILATION_FAILURE"
    ],
    "javaVersionUsedForReproduction": "11",
    "reproductionLogLocation": "reproduction/unreproducible/672d6123262b791a0a625c53470fad644e44871a.log"
  }
}