{
  "url": "https://github.com/apache/logging-log4j2/pull/881",
  "project": "logging-log4j2",
  "commit": "687b6fbc0b78d6a564910b14da4a159215acfda5",
  "createdAt": "2022-05-23 21:30:28",
  "dependencyGroupID": "org.eclipse.persistence",
  "dependencyArtifactID": "org.eclipse.persistence.jpa",
  "previousVersion": "2.7.10",
  "newVersion": "3.0.2",
  "versionUpdateType": "major",
  "type": "dependabot",
  "reproductionStatus": "unreproducible",
  "analysis": {
    "labels": [
      "PRECEDING_COMMIT_COMPILATION_FAILURE"
    ],
    "javaVersionUsedForReproduction": "11",
    "reproductionLogLocation": "reproduction/unreproducible/687b6fbc0b78d6a564910b14da4a159215acfda5.log"
  }
}