{
  "url": "https://github.com/apache/skywalking-java/pull/223",
  "project": "skywalking-java",
  "commit": "6afb427236a90f97c7605896bcacbb748f3253bd",
  "createdAt": "2022-06-21 04:23:30",
  "dependencyGroupID": "mysql",
  "dependencyArtifactID": "mysql-connector-java",
  "previousVersion": "5.1.25",
  "newVersion": "8.0.28",
  "versionUpdateType": "major",
  "type": "dependabot",
  "reproductionStatus": "unreproducible",
  "analysis": {
    "labels": [
      "PRECEDING_COMMIT_COMPILATION_FAILURE"
    ],
    "javaVersionUsedForReproduction": "11",
    "reproductionLogLocation": "reproduction/unreproducible/6afb427236a90f97c7605896bcacbb748f3253bd.log"
  }
}