{
  "url": "https://github.com/Pante/chimera/pull/238",
  "project": "chimera",
  "commit": "72076ca908c8fffeb5e37a0b1c5eef84c7339326",
  "createdAt": "2020-11-03T21:12:08.000+00:00",
  "dependencyGroupID": "org.checkerframework",
  "dependencyArtifactID": "checker-qual",
  "previousVersion": "3.7.0",
  "newVersion": "3.7.1",
  "versionUpdateType": "patch",
  "type": "dependabot",
  "reproductionStatus": "unreproducible",
  "analysis": {
    "labels": [
      "PRECEDING_COMMIT_COMPILATION_FAILURE"
    ],
    "javaVersionUsedForReproduction": "11",
    "reproductionLogLocation": "https://github.com/chains-project/breaking-updates/blob/main/reproduction/unreproducible/72076ca908c8fffeb5e37a0b1c5eef84c7339326.log"
  }
}