{
  "url": "https://github.com/sqlancer/sqlancer/pull/253",
  "project": "sqlancer",
  "commit": "729e39853fbbe750236993b35beec05d58d3612c",
  "createdAt": "2020-12-09T06:23:07.000+00:00",
  "dependencyGroupID": "org.xerial",
  "dependencyArtifactID": "sqlite-jdbc",
  "previousVersion": "3.32.3.2",
  "newVersion": "3.32.3.3",
  "versionUpdateType": "other",
  "type": "dependabot",
  "reproductionStatus": "successful",
  "analysis": {
    "labels": [
      "TEST_FAILURE"
    ],
    "javaVersionUsedForReproduction": "11",
    "reproductionLogLocation": "https://github.com/chains-project/breaking-updates/blob/main/reproduction/successful/729e39853fbbe750236993b35beec05d58d3612c.log"
  }
}