{
  "url" : "https://github.com/jvanzyl/provisio/pull/63",
  "project" : "provisio",
  "commit" : "78106a8a7d907f0311b4d3a712a36bd05fc712df",
  "createdAt" : "2023-05-12T18:35:15.000+00:00",
  "dependencyGroupID" : "org.scala-lang",
  "dependencyArtifactID" : "scala-library",
  "previousVersion" : "2.13.6",
  "newVersion" : "2.13.9",
  "dependencyScope" : "unknown",
  "versionUpdateType" : "patch",
  "type" : "dependabot",
  "baseBuildCommand" : null,
  "breakingUpdateReproductionCommand" : null,
  "reproductionStatus" : "not_attempted",
  "analysis" : null,
  "metadata" : null
}