{
  "url": "https://github.com/OneBusAway/onebusaway-gtfs-modules/pull/187",
  "project": "onebusaway-gtfs-modules",
  "commit": "7c62ae7f31ed9c994a9c1e6906fb9de391c1af5b",
  "createdAt": "2022-02-09 23:20:23",
  "dependencyGroupID": "org.hibernate",
  "dependencyArtifactID": "hibernate-core",
  "previousVersion": "4.0.1.Final",
  "newVersion": "5.4.24.Final",
  "versionUpdateType": "other",
  "type": "dependabot",
  "reproductionStatus": "successful",
  "analysis": {
    "labels": [
      "COMPILATION_FAILURE"
    ],
    "javaVersionUsedForReproduction": "11",
    "reproductionLogLocation": "reproduction/successful/7c62ae7f31ed9c994a9c1e6906fb9de391c1af5b.log"
  }
}