{
  "url": "https://github.com/International-Data-Spaces-Association/IDS-Messaging-Services/pull/434",
  "project": "IDS-Messaging-Services",
  "commit": "7ee23da1264442a0eaf3aa0f03bb0c2beba9cab7",
  "createdAt": "2022-02-17 19:11:07",
  "dependency": "org.springframework",
  "previousVersion": "5.3.15",
  "newVersion": "5.3.16",
  "versionUpdateType": "patch",
  "type": "dependabot",
  "reproductionStatus": "unreproducible",
  "analysis": {
    "labels": [
      "NO_FAILURE"
    ],
    "javaVersionUsedForReproduction": "11",
    "reproductionLogLocation": "./reproduction/unreproducible/7ee23da1264442a0eaf3aa0f03bb0c2beba9cab7.log"
  }
}