{
  "url" : "https://github.com/P2P-Develop/PeyangSuperbAntiCheat/pull/107",
  "project" : "PeyangSuperbAntiCheat",
  "commit" : "825f9423db3fb42899e5b7101354bf015c580e60",
  "createdAt" : "2022-01-25T20:03:57.000+00:00",
  "dependencyGroupID" : "org.slf4j",
  "dependencyArtifactID" : "slf4j-jdk14",
  "previousVersion" : "1.7.32",
  "newVersion" : "1.7.35",
  "dependencyScope" : "unknown",
  "versionUpdateType" : "patch",
  "prAuthor" : "bot",
  "preCommitAuthor" : "human",
  "breakingCommitAuthor" : "bot",
  "baseBuildCommand" : null,
  "breakingUpdateReproductionCommand" : null,
  "reproductionStatus" : "not_attempted",
  "analysis" : null,
  "metadata" : null
}