{
  "url" : "https://github.com/jenkinsci/maven-plugin/pull/202",
  "project" : "maven-plugin",
  "commit" : "86f9b7d5cf36952596657f486d5785c60058c5b8",
  "createdAt" : "2021-08-16T06:04:11.000+00:00",
  "dependencyGroupID" : "io.jenkins.tools.bom",
  "dependencyArtifactID" : "bom-2.289.x",
  "previousVersion" : "887.vae9c8ac09ff7",
  "newVersion" : "924.vda78166e6655",
  "dependencyScope" : "import",
  "versionUpdateType" : "other",
  "prAuthor" : "bot",
  "preCommitAuthor" : "bot",
  "breakingCommitAuthor" : "bot",
  "baseBuildCommand" : null,
  "breakingUpdateReproductionCommand" : null,
  "reproductionStatus" : "not_attempted",
  "analysis" : null,
  "metadata" : null
}