{
  "url": "https://github.com/google/auto/pull/1117",
  "project": "auto",
  "commit": "8907b4e77b33b1e6280bbea04a5ba3e16e180aed",
  "createdAt": "2021-06-16T05:47:20.000+00:00",
  "dependencyGroupID": "org.eclipse.jdt",
  "dependencyArtifactID": "ecj",
  "previousVersion": "3.25.0",
  "newVersion": "3.26.0",
  "versionUpdateType": "minor",
  "type": "dependabot",
  "reproductionStatus": "unreproducible",
  "analysis": {
    "labels": [
      "PRECEDING_COMMIT_COMPILATION_FAILURE"
    ],
    "javaVersionUsedForReproduction": "11",
    "reproductionLogLocation": "https://github.com/chains-project/breaking-updates/blob/main/reproduction/unreproducible/8907b4e77b33b1e6280bbea04a5ba3e16e180aed.log"
  }
}