{
  "url" : "https://github.com/jenkinsci/tekton-client-plugin/pull/331",
  "project" : "tekton-client-plugin",
  "commit" : "d1650d2c9fcc7364d51ee0a67fb8ecb4a214ac23",
  "createdAt" : "2023-06-05T19:57:31.000+00:00",
  "dependencyGroupID" : "org.jenkins-ci.plugins",
  "dependencyArtifactID" : "jackson2-api",
  "previousVersion" : "2.12.1",
  "newVersion" : "2.15.2-350.v0c2f3f8fc595",
  "dependencyScope" : "unknown",
  "versionUpdateType" : "other",
  "prAuthor" : "bot",
  "preCommitAuthor" : "human",
  "breakingCommitAuthor" : "bot",
  "baseBuildCommand" : null,
  "breakingUpdateReproductionCommand" : null,
  "reproductionStatus" : "not_attempted",
  "analysis" : null,
  "metadata" : null
}