{
  "url" : "https://github.com/jnidzwetzki/bitfinex-v2-wss-api-java/pull/323",
  "project" : "bitfinex-v2-wss-api-java",
  "projectOrganisation" : "jnidzwetzki",
  "breakingCommit" : "0ead9a6c759b422a5b8db197bb52d1cc0cabce78",
  "prAuthor" : "bot",
  "preCommitAuthor" : "bot",
  "breakingCommitAuthor" : "bot",
  "updatedDependency" : {
    "dependencyGroupID" : "org.json",
    "dependencyArtifactID" : "json",
    "previousVersion" : "20230227",
    "newVersion" : "20230618",
    "dependencyScope" : "compile",
    "versionUpdateType" : "other",
    "githubCompareLink" : "A GitHub repository could not be found for the updated dependency.",
    "mavenSourceLinkPre" : "https://repo1.maven.org/maven2/org/json/json/20230227/json-20230227-sources.jar",
    "mavenSourceLinkBreaking" : "https://repo1.maven.org/maven2/org/json/json/20230618/json-20230618-sources.jar",
    "updatedFileType" : "JAR",
    "dependencySection" : "dependencies",
    "licenseInfo" : "NOASSERTION",
    "githubRepoSlug" : "stleary/JSON-java"
  },
  "preCommitReproductionCommand" : "docker run ghcr.io/chains-project/breaking-updates:0ead9a6c759b422a5b8db197bb52d1cc0cabce78-pre",
  "breakingUpdateReproductionCommand" : "docker run ghcr.io/chains-project/breaking-updates:0ead9a6c759b422a5b8db197bb52d1cc0cabce78-breaking",
  "javaVersionUsedForReproduction" : "11",
  "failureCategory" : "TEST_FAILURE",
  "licenseInfo" : "Apache-2.0"
}