{
  "url" : "https://github.com/NemProject/nem/pull/211",
  "project" : "nem",
  "projectOrganisation" : "NemProject",
  "breakingCommit" : "a36653e160cca6bfcaedbfa5c0e25199d1b3a0b7",
  "prAuthor" : "bot",
  "preCommitAuthor" : "bot",
  "breakingCommitAuthor" : "bot",
  "updatedDependency" : {
    "dependencyGroupID" : "org.flywaydb",
    "dependencyArtifactID" : "flyway-core",
    "previousVersion" : "3.2.1",
    "newVersion" : "9.14.1",
    "dependencyScope" : "compile",
    "versionUpdateType" : "major",
    "githubCompareLink" : "A GitHub repository could not be found for the updated dependency.",
    "mavenSourceLinkPre" : "https://repo1.maven.org/maven2/org/flywaydb/flyway-core/3.2.1/flyway-core-3.2.1-sources.jar",
    "mavenSourceLinkBreaking" : "https://repo1.maven.org/maven2/org/flywaydb/flyway-core/9.14.1/flyway-core-9.14.1-sources.jar",
    "updatedFileType" : "JAR",
    "dependencySection" : "dependencies",
    "licenseInfo" : "Apache-2.0",
    "githubRepoSlug" : "flyway/flyway"
  },
  "preCommitReproductionCommand" : "docker run ghcr.io/chains-project/breaking-updates:a36653e160cca6bfcaedbfa5c0e25199d1b3a0b7-pre",
  "breakingUpdateReproductionCommand" : "docker run ghcr.io/chains-project/breaking-updates:a36653e160cca6bfcaedbfa5c0e25199d1b3a0b7-breaking",
  "javaVersionUsedForReproduction" : "11",
  "failureCategory" : "COMPILATION_FAILURE",
  "licenseInfo" : "MIT"
}