{
  "url": "https://github.com/jenkinsci/github-oauth-plugin/pull/188",
  "project": "github-oauth-plugin",
  "breakingCommit": "26064aa3340526ef7924d3736cbf3c6e449a9b61",
  "prAuthor": "bot",
  "preCommitAuthor": "human",
  "breakingCommitAuthor": "bot",
  "updatedDependency": {
    "dependencyGroupID": "org.jenkins-ci.plugins",
    "dependencyArtifactID": "github-branch-source",
    "previousVersion": "2.11.4",
    "newVersion": "1656.v77eddb_b_e95df",
    "dependencyScope": "compile",
    "versionUpdateType": "other"
  }
}