{
  "url" : "https://github.com/pinterest/singer/pull/243",
  "project" : "singer",
  "breakingCommit" : "2c5032708c84720a10a74cc88dc07437629f6b49",
  "prAuthor" : "human",
  "preCommitAuthor" : "human",
  "breakingCommitAuthor" : "human",
  "updatedDependency" : {
    "dependencyGroupID" : "com.amazonaws",
    "dependencyArtifactID" : "aws-java-sdk-core",
    "previousVersion" : "1.12.248",
    "newVersion" : "1.12.306",
    "dependencyScope" : "compile",
    "versionUpdateType" : "patch"
  }
}