{
  "url" : "https://github.com/razorpay/razorpay-java/pull/188",
  "project" : "razorpay-java",
  "breakingCommit" : "4e5e557f3480b3b19fc4ea4604994bb9d6aa0a81",
  "prAuthor" : "bot",
  "preCommitAuthor" : "human",
  "breakingCommitAuthor" : "bot",
  "updatedDependency" : {
    "dependencyGroupID" : "com.squareup.okhttp3",
    "dependencyArtifactID" : "logging-interceptor",
    "previousVersion" : "3.10.0",
    "newVersion" : "4.10.0",
    "dependencyScope" : "compile",
    "versionUpdateType" : "major"
  }
}