{
  "url": "https://github.com/jenkinsci/config-file-provider-plugin/pull/144",
  "project": "config-file-provider-plugin",
  "breakingCommit": "7192699a7a0b1d4e4d1981a7ea68bf91387bb229",
  "prAuthor": "bot",
  "preCommitAuthor": "human",
  "breakingCommitAuthor": "bot",
  "updatedDependency": {
    "dependencyGroupID": "io.jenkins.tools.bom",
    "dependencyArtifactID": "bom-2.277.x",
    "previousVersion": "29",
    "newVersion": "950.v396cb834de1e",
    "dependencyScope": "import",
    "versionUpdateType": "other"
  }
}