{
  "url": "https://github.com/jcabi/jcabi-http/pull/408",
  "project": "jcabi-http",
  "breakingCommit": "bd46a7fe95a386f4def45dcc8c6c18ba2d9a5920",
  "prAuthor": "bot",
  "preCommitAuthor": "bot",
  "breakingCommitAuthor": "bot",
  "updatedDependency": {
    "dependencyGroupID": "com.fasterxml.jackson.core",
    "dependencyArtifactID": "jackson-databind",
    "previousVersion": "2.14.1",
    "newVersion": "2.15.2",
    "dependencyScope": "provided",
    "versionUpdateType": "minor"
  }
}