{
  "url" : "https://github.com/aws/aws-encryption-sdk-java/pull/1656",
  "project" : "aws-encryption-sdk-java",
  "breakingCommit" : "d6c5f27278b733fd9348a55accb7431a58328d35",
  "prAuthor" : "bot",
  "preCommitAuthor" : "bot",
  "breakingCommitAuthor" : "bot",
  "updatedDependency" : {
    "dependencyGroupID" : "com.amazonaws",
    "dependencyArtifactID" : "aws-java-sdk",
    "previousVersion" : "1.12.394",
    "newVersion" : "1.12.490",
    "dependencyScope" : "compile",
    "versionUpdateType" : "patch"
  }
}