{
  "url" : "https://github.com/factcast/factcast/pull/2304",
  "project" : "factcast",
  "projectOrganisation" : "factcast",
  "breakingCommit" : "05b42741c6a4cbb5c4099714d15ca37870e45996",
  "prAuthor" : "bot",
  "preCommitAuthor" : "human",
  "breakingCommitAuthor" : "bot",
  "updatedDependency" : {
    "dependencyGroupID" : "com.google.guava",
    "dependencyArtifactID" : "guava",
    "previousVersion" : "31.1-jre",
    "newVersion" : "32.0.0-jre",
    "dependencyScope" : "compile",
    "versionUpdateType" : "other"
  },
  "javaVersionUsedForReproduction" : "11",
  "licenseInfo" : "Apache-2.0"
}