{
  "url" : "https://github.com/apache/logging-log4j2/pull/884",
  "project" : "logging-log4j2",
  "projectOrganisation" : "apache",
  "breakingCommit" : "076e2b383099f535e559cda98ba9ea1179046703",
  "prAuthor" : "bot",
  "preCommitAuthor" : "human",
  "breakingCommitAuthor" : "bot",
  "updatedDependency" : {
    "dependencyGroupID" : "org.hsqldb",
    "dependencyArtifactID" : "hsqldb",
    "previousVersion" : "2.5.2",
    "newVersion" : "2.6.1",
    "dependencyScope" : "compile",
    "versionUpdateType" : "minor"
  },
  "javaVersionUsedForReproduction" : "11",
  "licenseInfo" : "Apache-2.0"
}