{
  "url" : "https://github.com/approvals/ApprovalTests.Java/pull/275",
  "project" : "ApprovalTests.Java",
  "projectOrganisation" : "approvals",
  "breakingCommit" : "0a97c109b6715edf805aebb197cc7f821d826586",
  "prAuthor" : "bot",
  "preCommitAuthor" : "human",
  "breakingCommitAuthor" : "bot",
  "updatedDependency" : {
    "dependencyGroupID" : "org.apache.logging.log4j",
    "dependencyArtifactID" : "log4j-core",
    "previousVersion" : "2.17.2",
    "newVersion" : "2.18.0",
    "dependencyScope" : "compile",
    "versionUpdateType" : "minor"
  },
  "javaVersionUsedForReproduction" : "11"
}