{
  "url" : "https://github.com/chocoteam/choco-solver/pull/902",
  "project" : "choco-solver",
  "projectOrganisation" : "chocoteam",
  "breakingCommit" : "0dae361a67311154f33b697a7dbdc293c3f2f0e8",
  "prAuthor" : "bot",
  "preCommitAuthor" : "human",
  "breakingCommitAuthor" : "bot",
  "updatedDependency" : {
    "dependencyGroupID" : "org.antlr",
    "dependencyArtifactID" : "antlr4-runtime",
    "previousVersion" : "4.9.3",
    "newVersion" : "4.10.1",
    "dependencyScope" : "compile",
    "versionUpdateType" : "minor"
  },
  "javaVersionUsedForReproduction" : "11"
}