{
  "url" : "https://github.com/googleapis/java-datastore/pull/530",
  "project" : "java-datastore",
  "projectOrganisation" : "googleapis",
  "breakingCommit" : "1d0ecad2e464c392f6c5bbf1975123fef83d1890",
  "prAuthor" : "bot",
  "preCommitAuthor" : "human",
  "breakingCommitAuthor" : "bot",
  "updatedDependency" : {
    "dependencyGroupID" : "com.google.cloud",
    "dependencyArtifactID" : "libraries-bom",
    "previousVersion" : "22.0.0",
    "newVersion" : "23.0.0",
    "dependencyScope" : "import",
    "versionUpdateType" : "major"
  },
  "javaVersionUsedForReproduction" : "11"
}