{
  "url" : "https://github.com/LibrePlan/libreplan/pull/1958",
  "project" : "libreplan",
  "projectOrganisation" : "LibrePlan",
  "breakingCommit" : "214e707ecff0d6bf250fbdf08259813d20cbe1f4",
  "prAuthor" : "bot",
  "preCommitAuthor" : "human",
  "breakingCommitAuthor" : "bot",
  "updatedDependency" : {
    "dependencyGroupID" : "commons-fileupload",
    "dependencyArtifactID" : "commons-fileupload",
    "previousVersion" : "1.3.3",
    "newVersion" : "1.5",
    "dependencyScope" : "runtime",
    "versionUpdateType" : "minor",
    "licenseInfo" : "No license found",
    "githubRepoSlug" : "Repository not found"
  },
  "javaVersionUsedForReproduction" : "11",
  "licenseInfo" : "AGPL-3.0"
}