{
  "url" : "https://github.com/geonetwork/core-geonetwork/pull/7166",
  "project" : "core-geonetwork",
  "projectOrganisation" : "geonetwork",
  "breakingCommit" : "2e411f17f6d8113ed33203d16555bec4f1c157ce",
  "prAuthor" : "bot",
  "preCommitAuthor" : "human",
  "breakingCommitAuthor" : "bot",
  "updatedDependency" : {
    "dependencyGroupID" : "org.json",
    "dependencyArtifactID" : "json",
    "previousVersion" : "20140107",
    "newVersion" : "20230618",
    "dependencyScope" : "compile",
    "versionUpdateType" : "other",
    "licenseInfo" : "NOASSERTION",
    "githubRepoSlug" : "stleary/JSON-java"
  },
  "javaVersionUsedForReproduction" : "11",
  "licenseInfo" : "GPL-2.0"
}