{
  "url" : "https://github.com/jcabi/jcabi-matchers/pull/67",
  "project" : "jcabi-matchers",
  "projectOrganisation" : "jcabi",
  "breakingCommit" : "339b0ecfde638ebc5e1554981ae65a454b9c8290",
  "prAuthor" : "bot",
  "preCommitAuthor" : "human",
  "breakingCommitAuthor" : "bot",
  "updatedDependency" : {
    "dependencyGroupID" : "com.jcabi",
    "dependencyArtifactID" : "jcabi-log",
    "previousVersion" : "0.22.0",
    "newVersion" : "0.23.0",
    "dependencyScope" : "compile",
    "versionUpdateType" : "minor"
  },
  "javaVersionUsedForReproduction" : "11",
  "licenseInfo" : "NOASSERTION"
}