{
  "url" : "https://github.com/camunda-community-hub/zeebe-test-container/pull/438",
  "project" : "zeebe-test-container",
  "projectOrganisation" : "camunda-community-hub",
  "breakingCommit" : "5141e44054d29ae20dbfd7bf7fe5faa3948c8ccf",
  "prAuthor" : "bot",
  "preCommitAuthor" : "human",
  "breakingCommitAuthor" : "bot",
  "updatedDependency" : {
    "dependencyGroupID" : "net.bytebuddy",
    "dependencyArtifactID" : "byte-buddy",
    "previousVersion" : "1.13.0",
    "newVersion" : "1.14.0",
    "dependencyScope" : "compile",
    "versionUpdateType" : "minor"
  },
  "javaVersionUsedForReproduction" : "11"
}