{
  "url" : "https://github.com/ferstl/depgraph-maven-plugin/pull/174",
  "project" : "depgraph-maven-plugin",
  "projectOrganisation" : "ferstl",
  "breakingCommit" : "6d67b468edb8492437317711ebe198bee5a24bef",
  "prAuthor" : "bot",
  "preCommitAuthor" : "human",
  "breakingCommitAuthor" : "bot",
  "updatedDependency" : {
    "dependencyGroupID" : "com.google.guava",
    "dependencyArtifactID" : "guava",
    "previousVersion" : "31.1-jre",
    "newVersion" : "32.0.0-jre",
    "dependencyScope" : "compile",
    "versionUpdateType" : "other",
    "licenseInfo" : "No license found",
    "githubRepoSlug" : "Repository not found"
  },
  "javaVersionUsedForReproduction" : "11",
  "licenseInfo" : "Apache-2.0"
}