{
  "url" : "https://github.com/apache/incubator-hugegraph/pull/1758",
  "project" : "incubator-hugegraph",
  "projectOrganisation" : "apache",
  "breakingCommit" : "71bd8cc7744ca7795fd37985f578359c38e466fc",
  "prAuthor" : "bot",
  "preCommitAuthor" : "human",
  "breakingCommitAuthor" : "bot",
  "updatedDependency" : {
    "dependencyGroupID" : "org.postgresql",
    "dependencyArtifactID" : "postgresql",
    "previousVersion" : "42.1.4",
    "newVersion" : "42.3.3",
    "dependencyScope" : "compile",
    "versionUpdateType" : "minor"
  },
  "javaVersionUsedForReproduction" : "11"
}