{
  "url" : "https://github.com/primefaces/primefaces/pull/10421",
  "project" : "primefaces",
  "projectOrganisation" : "primefaces",
  "breakingCommit" : "75c1d23f01ebe2817ca3e655a5984c2f737eb499",
  "prAuthor" : "bot",
  "preCommitAuthor" : "human",
  "breakingCommitAuthor" : "bot",
  "updatedDependency" : {
    "dependencyGroupID" : "org.seleniumhq.selenium",
    "dependencyArtifactID" : "selenium-java",
    "previousVersion" : "4.10.0",
    "newVersion" : "4.11.0",
    "dependencyScope" : "compile",
    "versionUpdateType" : "minor",
    "dependencySection" : "dependencies",
    "licenseInfo" : "No license found",
    "githubRepoSlug" : "Repository not found"
  },
  "javaVersionUsedForReproduction" : "11",
  "licenseInfo" : "MIT"
}