{
  "url" : "https://github.com/javaparser/javaparser/pull/4042",
  "project" : "javaparser",
  "projectOrganisation" : "javaparser",
  "breakingCommit" : "78b4e5695398502f320c68240b8cb8d9fe06e18e",
  "prAuthor" : "bot",
  "preCommitAuthor" : "human",
  "breakingCommitAuthor" : "bot",
  "updatedDependency" : {
    "dependencyGroupID" : "com.google.guava",
    "dependencyArtifactID" : "guava",
    "previousVersion" : "31.1-jre",
    "newVersion" : "32.0.0-jre",
    "dependencyScope" : "compile",
    "versionUpdateType" : "other",
    "licenseInfo" : "No license found",
    "githubRepoSlug" : "Repository not found"
  },
  "javaVersionUsedForReproduction" : "11",
  "licenseInfo" : "NOASSERTION"
}