{
  "url" : "https://github.com/jenkinsci/declarative-pipeline-migration-assistant-plugin/pull/102",
  "project" : "declarative-pipeline-migration-assistant-plugin",
  "breakingCommit" : "81be13babd38ec19ddb497371a06e81935dfc2ba",
  "prAuthor" : "bot",
  "preCommitAuthor" : "bot",
  "breakingCommitAuthor" : "bot",
  "updatedDependency" : {
    "dependencyGroupID" : "org.jenkins-ci.plugins",
    "dependencyArtifactID" : "htmlpublisher",
    "previousVersion" : "1.23",
    "newVersion" : "1.26",
    "dependencyScope" : "compile",
    "versionUpdateType" : "other"
  },
  "javaVersionUsedForReproduction" : "11"
}