{
  "url" : "https://github.com/mirkosertic/GameComposer/pull/399",
  "project" : "GameComposer",
  "projectOrganisation" : "mirkosertic",
  "breakingCommit" : "86c2187f37205886e8924d7af067a9073b60e00f",
  "prAuthor" : "bot",
  "preCommitAuthor" : "bot",
  "breakingCommitAuthor" : "bot",
  "updatedDependency" : {
    "dependencyGroupID" : "org.springframework.boot",
    "dependencyArtifactID" : "spring-boot-starter-web",
    "previousVersion" : "2.7.3",
    "newVersion" : "2.7.5",
    "dependencyScope" : "compile",
    "versionUpdateType" : "patch"
  },
  "javaVersionUsedForReproduction" : "11"
}