{
  "url" : "https://github.com/spotify/dbeam/pull/436",
  "project" : "dbeam",
  "projectOrganisation" : "spotify",
  "breakingCommit" : "a18d37efc1d15247ae39594e6ff6909d085519b7",
  "prAuthor" : "bot",
  "preCommitAuthor" : "human",
  "breakingCommitAuthor" : "bot",
  "updatedDependency" : {
    "dependencyGroupID" : "com.google.apis",
    "dependencyArtifactID" : "google-api-services-cloudkms",
    "previousVersion" : "v1-rev20211130-1.32.1",
    "newVersion" : "v1-rev20220211-1.32.1",
    "dependencyScope" : "compile",
    "versionUpdateType" : "other"
  },
  "javaVersionUsedForReproduction" : "11",
  "licenseInfo" : "Apache-2.0"
}