{
  "url" : "https://github.com/quarkusio/quarkus-platform/pull/419",
  "project" : "quarkus-platform",
  "projectOrganisation" : "quarkusio",
  "breakingCommit" : "a61c0dbe8a400182984b6af2ca0690b2510db782",
  "prAuthor" : "bot",
  "preCommitAuthor" : "human",
  "breakingCommitAuthor" : "bot",
  "updatedDependency" : {
    "dependencyGroupID" : "org.apache.logging.log4j",
    "dependencyArtifactID" : "log4j-api",
    "previousVersion" : "2.16.0",
    "newVersion" : "2.17.1",
    "dependencyScope" : "compile",
    "versionUpdateType" : "minor",
    "licenseInfo" : "Apache-2.0",
    "githubRepoSlug" : "apache/logging-log4j1"
  },
  "javaVersionUsedForReproduction" : "11",
  "licenseInfo" : "Apache-2.0"
}