{
  "url" : "https://github.com/informatici/openhospital-core/pull/850",
  "project" : "openhospital-core",
  "projectOrganisation" : "informatici",
  "breakingCommit" : "a7efc6b1e6fde7d8c05f1453feabd73cf3894cf9",
  "prAuthor" : "bot",
  "preCommitAuthor" : "human",
  "breakingCommitAuthor" : "bot",
  "updatedDependency" : {
    "dependencyGroupID" : "org.dcm4che",
    "dependencyArtifactID" : "dcm4che-core",
    "previousVersion" : "5.29.1",
    "newVersion" : "5.29.2",
    "dependencyScope" : "compile",
    "versionUpdateType" : "patch"
  },
  "javaVersionUsedForReproduction" : "11"
}