{
  "url" : "https://github.com/paulcwarren/spring-content-examples/pull/965",
  "project" : "spring-content-examples",
  "projectOrganisation" : "paulcwarren",
  "breakingCommit" : "abd98eba3dd2e0c89aa367bfef64a29aab70febe",
  "prAuthor" : "bot",
  "preCommitAuthor" : "human",
  "breakingCommitAuthor" : "bot",
  "updatedDependency" : {
    "dependencyGroupID" : "software.amazon.awssdk",
    "dependencyArtifactID" : "netty-nio-client",
    "previousVersion" : "2.18.38",
    "newVersion" : "2.20.31",
    "dependencyScope" : "compile",
    "versionUpdateType" : "minor",
    "licenseInfo" : "No license found",
    "githubRepoSlug" : "Repository not found"
  },
  "javaVersionUsedForReproduction" : "11",
  "licenseInfo" : "No license found"
}