{
  "url" : "https://github.com/sqlancer/sqlancer/pull/589",
  "project" : "sqlancer",
  "projectOrganisation" : "sqlancer",
  "breakingCommit" : "b0bb5cb31afa6eb75d255d1040b7cffc78cfcad6",
  "prAuthor" : "bot",
  "preCommitAuthor" : "human",
  "breakingCommitAuthor" : "bot",
  "updatedDependency" : {
    "dependencyGroupID" : "org.questdb",
    "dependencyArtifactID" : "questdb",
    "previousVersion" : "6.5.3",
    "newVersion" : "6.5.3-jdk8",
    "dependencyScope" : "compile",
    "versionUpdateType" : "other"
  },
  "javaVersionUsedForReproduction" : "11"
}