{
  "url" : "https://github.com/MorphiaOrg/morphia/pull/2285",
  "project" : "morphia",
  "projectOrganisation" : "MorphiaOrg",
  "breakingCommit" : "bbb38ceacf24aba4d5fd552567874748a1a65fab",
  "prAuthor" : "bot",
  "preCommitAuthor" : "bot",
  "breakingCommitAuthor" : "bot",
  "updatedDependency" : {
    "dependencyGroupID" : "net.bytebuddy",
    "dependencyArtifactID" : "byte-buddy",
    "previousVersion" : "1.14.0",
    "newVersion" : "1.14.1",
    "dependencyScope" : "compile",
    "versionUpdateType" : "patch",
    "licenseInfo" : "No license found",
    "githubRepoSlug" : "Repository not found"
  },
  "javaVersionUsedForReproduction" : "11",
  "licenseInfo" : "Apache-2.0"
}