{
  "url" : "https://github.com/btrplace/scheduler/pull/342",
  "project" : "scheduler",
  "breakingCommit" : "bfdd6b294d1b7b75bb5c851a1056d9d9b832637b",
  "prAuthor" : "bot",
  "preCommitAuthor" : "human",
  "breakingCommitAuthor" : "bot",
  "updatedDependency" : {
    "dependencyGroupID" : "ch.qos.logback",
    "dependencyArtifactID" : "logback-classic",
    "previousVersion" : "1.2.7",
    "newVersion" : "1.2.9",
    "dependencyScope" : "compile",
    "versionUpdateType" : "patch"
  },
  "javaVersionUsedForReproduction" : "11"
}