{
  "url" : "https://github.com/fmtn/a/pull/150",
  "project" : "a",
  "projectOrganisation" : "fmtn",
  "breakingCommit" : "c6809c0239937752ad71a4c38c274e51fcfb8b05",
  "prAuthor" : "bot",
  "preCommitAuthor" : "human",
  "breakingCommitAuthor" : "bot",
  "updatedDependency" : {
    "dependencyGroupID" : "org.graalvm.js",
    "dependencyArtifactID" : "js-scriptengine",
    "previousVersion" : "22.0.0",
    "newVersion" : "22.2.0",
    "dependencyScope" : "compile",
    "versionUpdateType" : "minor"
  },
  "javaVersionUsedForReproduction" : "11"
}