{
  "url" : "https://github.com/mork-optimization/mork/pull/115",
  "project" : "mork",
  "projectOrganisation" : "mork-optimization",
  "breakingCommit" : "c87cdaf1fa3ee129678cce52e73757e236defe70",
  "prAuthor" : "bot",
  "preCommitAuthor" : "human",
  "breakingCommitAuthor" : "bot",
  "updatedDependency" : {
    "dependencyGroupID" : "org.springframework",
    "dependencyArtifactID" : "spring-context",
    "previousVersion" : "5.3.24",
    "newVersion" : "6.0.0",
    "dependencyScope" : "compile",
    "versionUpdateType" : "major",
    "licenseInfo" : "Apache-2.0",
    "githubRepoSlug" : "spring-projects/spring-framework"
  },
  "javaVersionUsedForReproduction" : "11",
  "licenseInfo" : "MIT"
}