{
  "url" : "https://github.com/quarkusio/quarkus-platform/pull/423",
  "project" : "quarkus-platform",
  "projectOrganisation" : "quarkusio",
  "breakingCommit" : "e5230a4246693ba719844f920d5b97a5bc570e0d",
  "prAuthor" : "bot",
  "preCommitAuthor" : "human",
  "breakingCommitAuthor" : "bot",
  "updatedDependency" : {
    "dependencyGroupID" : "com.h2database",
    "dependencyArtifactID" : "h2",
    "previousVersion" : "1.4.197",
    "newVersion" : "2.0.206",
    "dependencyScope" : "compile",
    "versionUpdateType" : "major",
    "licenseInfo" : "NOASSERTION",
    "githubRepoSlug" : "h2database/h2database"
  },
  "javaVersionUsedForReproduction" : "11",
  "licenseInfo" : "Apache-2.0"
}