{
  "url" : "https://github.com/querydsl/querydsl/pull/3489",
  "project" : "querydsl",
  "projectOrganisation" : "querydsl",
  "breakingCommit" : "f0eb2190d7db244aa80f4972598b42b1f5f28740",
  "prAuthor" : "bot",
  "preCommitAuthor" : "bot",
  "breakingCommitAuthor" : "bot",
  "updatedDependency" : {
    "dependencyGroupID" : "org.springframework.boot",
    "dependencyArtifactID" : "spring-boot-starter-parent",
    "previousVersion" : "2.6.7",
    "newVersion" : "3.0.4",
    "dependencyScope" : "import",
    "versionUpdateType" : "major",
    "licenseInfo" : "Apache-2.0",
    "githubRepoSlug" : "spring-projects/spring-boot"
  },
  "javaVersionUsedForReproduction" : "11",
  "licenseInfo" : "Apache-2.0"
}