{
  "url" : "https://github.com/paulcwarren/spring-content-gettingstarted/pull/205",
  "project" : "spring-content-gettingstarted",
  "breakingCommit" : "fc96a04bf6f8b6a253edfece1ae0a9a7d423868d",
  "prAuthor" : "bot",
  "preCommitAuthor" : "bot",
  "breakingCommitAuthor" : "bot",
  "updatedDependency" : {
    "dependencyGroupID" : "org.testcontainers",
    "dependencyArtifactID" : "vault",
    "previousVersion" : "1.17.6",
    "newVersion" : "1.18.2",
    "dependencyScope" : "compile",
    "versionUpdateType" : "minor"
  },
  "javaVersionUsedForReproduction" : "11"
}