{
  "url" : "https://github.com/informatici/openhospital-core/pull/432",
  "project" : "openhospital-core",
  "projectOrganisation" : "informatici",
  "breakingCommit" : "feafeff72a8a8b602dfb368bbf8f4d5e071b3a12",
  "prAuthor" : "bot",
  "preCommitAuthor" : "bot",
  "breakingCommitAuthor" : "bot",
  "updatedDependency" : {
    "dependencyGroupID" : "org.springframework.data",
    "dependencyArtifactID" : "spring-data-jpa",
    "previousVersion" : "1.11.23.RELEASE",
    "newVersion" : "2.5.2",
    "dependencyScope" : "compile",
    "versionUpdateType" : "other",
    "licenseInfo" : "Apache-2.0",
    "githubRepoSlug" : "spring-projects/spring-data-jpa"
  },
  "javaVersionUsedForReproduction" : "11",
  "licenseInfo" : "GPL-3.0"
}